WCFkCenters
