Metadata-Version: 2.1
Name: wcfkcenters
Version: 0.0.7
Summary: A python package for Weighted Cluster Fuzzy-k-Centers algorithm
Home-page: https://github.com/
Author: ktstt
Author-email: toan_stt@yahoo.com
License: UNKNOWN
Platform: UNKNOWN
Classifier: Programming Language :: Python :: 3
Classifier: License :: OSI Approved :: MIT License
Classifier: Operating System :: OS Independent
Requires-Python: >=3.6
